explabox_demo_drugreview/__init__.py
explabox_demo_drugreview/assets/drugsCom.zip
explabox_demo_drugreview/assets/tokenizer.pkl
explabox_demo_drugreview-1.0.0.dist-info/METADATA
explabox_demo_drugreview-1.0.0.dist-info/WHEEL
explabox_demo_drugreview-1.0.0.dist-info/top_level.txt
explabox_demo_drugreview-1.0.0.dist-info/RECORD
