Metadata-Version: 2.1
Name: explabox-demo-drugreview
Version: 1.0.0
Summary: Explabox demo for the UCI drug reviews dataset
Author: NPAI
Requires-Python: >=3.8
Requires-Dist: explabox (>=0.9b7)
Requires-Dist: jupyter (>=1.0.0)
Requires-Dist: tokenizers (>=0.11.6)
Requires-Dist: transformers
Requires-Dist: tqdm (>=4.62.3)
Requires-Dist: filesplit (>=4.1.0)
